gatool-1.0.1.dist-info/top_level.txt
gatool-1.0.1.dist-info/METADATA
gatool-1.0.1.dist-info/RECORD
gatool-1.0.1.dist-info/DESCRIPTION.rst
gatool-1.0.1.dist-info/WHEEL
gatool-1.0.1.dist-info/metadata.json
gatool-1.0.1.data/scripts/gatool.py
ev/Initializators.py
ev/Mutators.py
ev/__init__.py
