Metadata-Version: 2.0
Name: gatool
Version: 1.0.1
Summary: Utility for console applications parameters adjustment with genetic algorithm
Home-page: https://github.com/lamerman/gatool
Author: Alexander Ponomarev
Author-email: alexander996@yandex.ru
License: BSD
Platform: Independent
Classifier: Development Status :: 5 - Production/Stable
Classifier: Intended Audience :: Developers
Classifier: Operating System :: OS Independent
Classifier: Programming Language :: Python
Classifier: Topic :: Software Development :: Libraries
Requires-Dist: pyevolve
